README.md
src/xwnode_wrapper.py
xwnode-0.0.1.26.dist-info/METADATA
xwnode-0.0.1.26.dist-info/WHEEL
xwnode-0.0.1.26.dist-info/licenses/LICENSE
xwnode-0.0.1.26.dist-info/RECORD
