Metadata-Version: 2.4
Name: xwnode
Version: 0.0.1.26
Summary: Convenience wrapper for exonware-xwnode - provides 'import xwnode' alias
Project-URL: Homepage, https://exonware.com
Project-URL: Repository, https://github.com/exonware/xwnode
Project-URL: Documentation, https://github.com/exonware/xwnode#readme
Author-email: "Eng. Muhammad AlShehri" <connect@exonware.com>
License: MIT
License-File: LICENSE
Keywords: computation,data-processing,exonware,graph,node,workflow
Classifier: Development Status :: 3 - Alpha
Classifier: Intended Audience :: Developers
Classifier: License :: OSI Approved :: MIT License
Classifier: Operating System :: OS Independent
Classifier: Programming Language :: Python :: 3
Classifier: Programming Language :: Python :: 3.8
Classifier: Programming Language :: Python :: 3.9
Classifier: Programming Language :: Python :: 3.10
Classifier: Programming Language :: Python :: 3.11
Classifier: Programming Language :: Python :: 3.12
Classifier: Topic :: Software Development :: Libraries :: Python Modules
Requires-Python: >=3.8
Requires-Dist: exonware-xwnode
Provides-Extra: dev
Requires-Dist: exonware-xwnode[dev]; extra == 'dev'
Provides-Extra: full
Requires-Dist: exonware-xwnode[full]; extra == 'full'
Provides-Extra: lazy
Requires-Dist: exonware-xwnode[lazy]; extra == 'lazy'
